<?xml version="1.0" encoding="UTF-8"?>
<objects serializationModel="Studio.02.02.00">
	<object class="AudioFile" id="{51b44a40-9879-4e56-960e-116a76c8096f}">
		<property name="assetPath">
			<value>Stuff i cant be bothered to sort/83528__tito-lahaye__tree-frog - Trimmed.wav</value>
		</property>
		<property name="frequencyInKHz">
			<value>44.0999985</value>
		</property>
		<property name="channelCount">
			<value>2</value>
		</property>
		<property name="length">
			<value>1.1999773242630385</value>
		</property>
		<relationship name="masterAssetFolder">
			<destination>{bdead0e8-a4a5-4374-b39b-4c32ed246587}</destination>
		</relationship>
	</object>
</objects>
